{
  "RSpec": {
    "coverage": {
      "/Users/pattaradanaisrichon/Desktop/Project/ttd-refactor-kata/ruby/src/gilded_rose.rb": {
        "lines": [
          1,
          null,
          1,
          10,
          null,
          null,
          1,
          10,
          62,
          16,
          16,
          null,
          null,
          46,
          5,
          5,
          null,
          null,
          41,
          16,
          16,
          null,
          null,
          25,
          null,
          null,
          null,
          1,
          null,
          1,
          25,
          25,
          0,
          null,
          null,
          25,
          17,
          17,
          null,
          null,
          8,
          null,
          null,
          1,
          16,
          null,
          16,
          8,
          null,
          8,
          null,
          null,
          null,
          1,
          5,
          null,
          null,
          5,
          1,
          4,
          2,
          2,
          1,
          null,
          1,
          null,
          null,
          null,
          1,
          16,
          16,
          0,
          null,
          null,
          16,
          8,
          8,
          null,
          null,
          8,
          null,
          null
        ]
      },
      "/Users/pattaradanaisrichon/Desktop/Project/ttd-refactor-kata/ruby/src/item.rb": {
        "lines": [
          1,
          1,
          null,
          1,
          63,
          63,
          63,
          null,
          null,
          1,
          0,
          null
        ]
      }
    },
    "timestamp": 1744778792
  }
}
